{
  "schemaVersion": 1,
  "bookSlug": "meyve-risalesi",
  "partNo": "p83",
  "gradeSlug": "11-sinif",
  "sourcePath": "../../meyve-risalesi/backup-old-20260614-174343/11-sinif/SEL_11sinif_meyve-risalesi-p83-10-mesele-lahika-husrevin-mektubu-riza-sadakat-ve-af-siari.json",
  "cardCount": 24,
  "selection": {
    "source": "SEL",
    "requestedCount": 24,
    "rule": "Dependency-complete first 24 questions from the question-sheet selection order."
  },
  "sets": [
    {
      "setNumber": 1,
      "questions": [
        {
          "id": "S1Q1",
          "setNumber": 1,
          "questionNumber": 1,
          "question": "Bu parçada talebelerin hangi manevi kaynaklardan ve kimlerden razı oldukları belirtilmektedir?",
          "answer": "Allah’tan, Kur’an’dan, Peygamber Efendimizden, Risale-i Nur’dan ve bu hizmette rehberlik eden üstadlarından hoşnut oldukları ifade edilmektedir.",
          "wordCount": 16,
          "selectedSetNumber": 1,
          "selectedQuestionNumber": 1,
          "sheetQuestionIndex": 1,
          "flashcardIndex": 1
        },
        {
          "id": "S1Q2",
          "setNumber": 1,
          "questionNumber": 2,
          "question": "Metinde bağlılık duydukları yoldan dolayı nasıl bir his taşıdıkları anlatılmaktadır?",
          "answer": "Bu mensubiyetten dolayı hiçbir pişmanlık duymadıkları bildirilmektedir.",
          "wordCount": 7,
          "selectedSetNumber": 1,
          "selectedQuestionNumber": 2,
          "sheetQuestionIndex": 2,
          "flashcardIndex": 2
        },
        {
          "id": "S1Q3",
          "setNumber": 1,
          "questionNumber": 3,
          "question": "Kalplerindeki niyetin hangi yönde olduğu özellikle vurgulanmaktadır?",
          "answer": "Kötülüğe yönelme niyetlerinin bulunmadığı, asıl gayelerinin Allah’ın rızasını kazanmak olduğu söylenmektedir.",
          "wordCount": 11,
          "selectedSetNumber": 1,
          "selectedQuestionNumber": 3,
          "sheetQuestionIndex": 3,
          "flashcardIndex": 3
        },
        {
          "id": "S1Q4",
          "setNumber": 1,
          "questionNumber": 4,
          "question": "Günler geçtikçe iç dünyalarında güçlenen arzu nedir?",
          "answer": "Allah’ın rızası içinde O’na kavuşma özlemlerinin arttığı anlatılmaktadır.",
          "wordCount": 8,
          "selectedSetNumber": 1,
          "selectedQuestionNumber": 4,
          "sheetQuestionIndex": 4,
          "flashcardIndex": 4
        },
        {
          "id": "S1Q5",
          "setNumber": 1,
          "questionNumber": 5,
          "question": "Kendilerine kötülük yapanlara karşı nasıl bir tavır benimsedikleri belirtiliyor?",
          "answer": "Onları Allah’a havale ederek bağışlamayı tercih ettikleri ifade ediliyor.",
          "wordCount": 9,
          "selectedSetNumber": 1,
          "selectedQuestionNumber": 5,
          "sheetQuestionIndex": 5,
          "flashcardIndex": 5
        },
        {
          "id": "S1Q6",
          "setNumber": 1,
          "questionNumber": 6,
          "question": "Sadece affetmekle yetinmeyip insanlara karşı nasıl bir tutum göstermeyi esas alıyorlar?",
          "answer": "Herkese iyilik yapmayı bir prensip haline getirdikleri belirtiliyor.",
          "wordCount": 8,
          "selectedSetNumber": 1,
          "selectedQuestionNumber": 6,
          "sheetQuestionIndex": 6,
          "flashcardIndex": 6
        },
        {
          "id": "S1Q7",
          "setNumber": 1,
          "questionNumber": 7,
          "question": "Zulmeden kimseler bu iyilik anlayışının dışında mı bırakılmaktadır?",
          "answer": "Hayır, zulmedenler de buna dâhil edilerek onlara karşı da iyilik düşüncesi korunmaktadır.",
          "wordCount": 12,
          "selectedSetNumber": 1,
          "selectedQuestionNumber": 7,
          "sheetQuestionIndex": 7,
          "flashcardIndex": 7
        },
        {
          "id": "S1Q8",
          "setNumber": 1,
          "questionNumber": 8,
          "question": "Bu ahlaki tavrın Risale-i Nur talebelerinin kalbinde nasıl bir yere sahip olduğu anlatılıyor?",
          "answer": "Bunun onların gönlünde yerleşmiş bir İslam düsturu olduğu belirtiliyor.",
          "wordCount": 9,
          "selectedSetNumber": 1,
          "selectedQuestionNumber": 8,
          "sheetQuestionIndex": 8,
          "flashcardIndex": 8
        },
        {
          "id": "S1Q9",
          "setNumber": 1,
          "questionNumber": 9,
          "question": "Metinde bu güzel halin ortaya çıkmasında kime şükredilmektedir?",
          "answer": "Bunu açığa çıkaran Allah’a sonsuz şükür edildiği bildirilmektedir.",
          "wordCount": 8,
          "selectedSetNumber": 1,
          "selectedQuestionNumber": 9,
          "sheetQuestionIndex": 9,
          "flashcardIndex": 9
        },
        {
          "id": "S1Q10",
          "setNumber": 1,
          "questionNumber": 10,
          "question": "Parçanın genel mesajı bir cümleyle nasıl özetlenebilir?",
          "answer": "Hak yoluna samimiyetle bağlanan kimselerin amacı Allah’ın rızasıdır; bu da onları affa, iyiliğe ve manevi olgunluğa yöneltir.",
          "wordCount": 17,
          "selectedSetNumber": 1,
          "selectedQuestionNumber": 10,
          "sheetQuestionIndex": 10,
          "flashcardIndex": 10
        },
        {
          "id": "S2Q1",
          "setNumber": 2,
          "questionNumber": 1,
          "question": "Parçada konuşan kişinin bağlılığını dile getirdiği manevi çizginin temel unsurları nelerdir?",
          "answer": "İlahi rıza, Kur’an, Peygamber sevgisi, Risale-i Nur hizmeti ve bu hizmetteki üstad bağı öne çıkarılmaktadır.",
          "wordCount": 15,
          "selectedSetNumber": 2,
          "selectedQuestionNumber": 1,
          "sheetQuestionIndex": 11,
          "flashcardIndex": 11
        },
        {
          "id": "S2Q2",
          "setNumber": 2,
          "questionNumber": 2,
          "question": "Bu bağlılığın geçici bir heyecan mı yoksa kararlı bir tercih mi olduğu nasıl anlaşılmaktadır?",
          "answer": "Hiçbir yönden pişmanlık bulunmadığının söylenmesi, bunun kararlı bir tercih olduğunu göstermektedir.",
          "wordCount": 11,
          "selectedSetNumber": 2,
          "selectedQuestionNumber": 2,
          "sheetQuestionIndex": 12,
          "flashcardIndex": 12
        },
        {
          "id": "S2Q3",
          "setNumber": 2,
          "questionNumber": 3,
          "question": "İç dünyalarında kötü bir amaç bulunmadığını söylemeleri, onların ahlakı hakkında ne gösterir?",
          "answer": "Samimiyet, temiz niyet ve zarar vermekten uzak bir karakter taşıdıklarını gösterir.",
          "wordCount": 11,
          "selectedSetNumber": 2,
          "selectedQuestionNumber": 3,
          "sheetQuestionIndex": 13,
          "flashcardIndex": 13
        },
        {
          "id": "S2Q4",
          "setNumber": 2,
          "questionNumber": 4,
          "question": "“Sadece Allah’ın rızasını istemek” ifadesi, hayat hedefleri açısından ne anlam taşır?",
          "answer": "Dünyevi çıkarları öne almadan asıl amaçlarını ilahi hoşnutluk olarak belirlediklerini gösterir.",
          "wordCount": 11,
          "selectedSetNumber": 2,
          "selectedQuestionNumber": 4,
          "sheetQuestionIndex": 14,
          "flashcardIndex": 14
        },
        {
          "id": "S2Q5",
          "setNumber": 2,
          "questionNumber": 5,
          "question": "Zaman ilerledikçe artan manevi istek, iman hayatının hangi yönüne işaret eder?",
          "answer": "Manevi olgunlaşmaya ve Allah’a yakınlaşma arzusunun derinleşmesine işaret eder.",
          "wordCount": 9,
          "selectedSetNumber": 2,
          "selectedQuestionNumber": 5,
          "sheetQuestionIndex": 15,
          "flashcardIndex": 15
        },
        {
          "id": "S2Q6",
          "setNumber": 2,
          "questionNumber": 6,
          "question": "Kendilerine haksızlık edenleri Allah’a bırakmaları hangi inanç ve teslimiyet anlayışını yansıtır?",
          "answer": "Son hükmün Allah’a ait olduğuna inanmayı ve kişisel intikamdan uzak durmayı yansıtır.",
          "wordCount": 12,
          "selectedSetNumber": 2,
          "selectedQuestionNumber": 6,
          "sheetQuestionIndex": 16,
          "flashcardIndex": 16
        },
        {
          "id": "S2Q7",
          "setNumber": 2,
          "questionNumber": 7,
          "question": "Affetmekle birlikte iyilik etmeyi sürdürmeleri hangi yüksek ahlaki seviyeyi gösterir?",
          "answer": "Kötülüğe kötülükle değil, güzel davranışla karşılık verme olgunluğunu gösterir.",
          "wordCount": 9,
          "selectedSetNumber": 2,
          "selectedQuestionNumber": 7,
          "sheetQuestionIndex": 17,
          "flashcardIndex": 17
        },
        {
          "id": "S2Q8",
          "setNumber": 2,
          "questionNumber": 8,
          "question": "Bu davranış biçiminin “İslam şiarı” sayılması neyi anlatır?",
          "answer": "Bunun sadece bireysel bir tercih değil, dine uygun ve örnek bir ahlak ölçüsü olduğunu anlatır.",
          "wordCount": 15,
          "selectedSetNumber": 2,
          "selectedQuestionNumber": 8,
          "sheetQuestionIndex": 18,
          "flashcardIndex": 18
        },
        {
          "id": "S2Q9",
          "setNumber": 2,
          "questionNumber": 9,
          "question": "Metinde geçen şükür duygusu hangi sebeple dile getirilmektedir?",
          "answer": "Bu güzel ahlakın kendi içlerinde yerleşmiş olmasına ve bunun ortaya çıkmasına vesile olan ilahi lütfa şükredilmektedir.",
          "wordCount": 16,
          "selectedSetNumber": 2,
          "selectedQuestionNumber": 9,
          "sheetQuestionIndex": 19,
          "flashcardIndex": 19
        },
        {
          "id": "S2Q10",
          "setNumber": 2,
          "questionNumber": 10,
          "question": "Parçadan hareketle bu talebelerin insanlarla ilişkilerinde öne çıkan üç özellik nedir?",
          "answer": "Sadakat, affedicilik ve iyilikseverliktir.",
          "wordCount": 4,
          "selectedSetNumber": 2,
          "selectedQuestionNumber": 10,
          "sheetQuestionIndex": 20,
          "flashcardIndex": 20
        },
        {
          "id": "S3Q1",
          "setNumber": 3,
          "questionNumber": 1,
          "question": "Bu bölümde talebelerin memnuniyet duydukları beş kaynak veya şahsiyet hangileridir?",
          "answer": "Allah, Kur’an, Resûl-i Ekrem, Risale-i Nur ve kendilerine rehber olan üstad zikredilmektedir.",
          "wordCount": 12,
          "selectedSetNumber": 3,
          "selectedQuestionNumber": 1,
          "sheetQuestionIndex": 21,
          "flashcardIndex": 21
        },
        {
          "id": "S3Q2",
          "setNumber": 3,
          "questionNumber": 2,
          "question": "Bağlı bulundukları hizmet yoluna dair ruh hâlleri nasıl ifade edilmektedir?",
          "answer": "Bundan dolayı içlerinde en küçük bir pişmanlık olmadığı belirtilmektedir.",
          "wordCount": 9,
          "selectedSetNumber": 3,
          "selectedQuestionNumber": 2,
          "sheetQuestionIndex": 22,
          "flashcardIndex": 22
        },
        {
          "id": "S3Q3",
          "setNumber": 3,
          "questionNumber": 3,
          "question": "Kalpte kötülük niyetinin bulunmaması, dış davranışlara nasıl yansıyabilir?",
          "answer": "İnsanlara zarar vermekten kaçınma, yumuşak davranma ve temiz bir ilişki kurma şeklinde yansıyabilir.",
          "wordCount": 13,
          "selectedSetNumber": 3,
          "selectedQuestionNumber": 3,
          "sheetQuestionIndex": 23,
          "flashcardIndex": 23
        },
        {
          "id": "S3Q4",
          "setNumber": 3,
          "questionNumber": 4,
          "question": "Metinde en çok istenen şey nedir?",
          "answer": "Allah’ın hoşnutluğunu kazanmak istenmektedir.",
          "wordCount": 4,
          "selectedSetNumber": 3,
          "selectedQuestionNumber": 4,
          "sheetQuestionIndex": 24,
          "flashcardIndex": 24
        }
      ]
    }
  ],
  "title": "10. Mes'ele / Lâhika: Hüsrev'in mektubu (rıza-sadakat ve af şiarı)"
}
