{
  "schemaVersion": 1,
  "catalogVersion": 1,
  "key": "ayetul-kubra:5-sinif:p114",
  "bookSlug": "ayetul-kubra",
  "bookTitle": "Ayetül Kübra",
  "bookOrder": 0,
  "gradeSlug": "5-sinif",
  "partNo": "p114",
  "partNumber": 114,
  "title": "Netice: Dua ve kapanış hamdi",
  "sourcePath": "C:/Users/musta/source/repos/TextDataEditor/sourceLib/data/AyetulKubra/5-sinif/SveC_5sinif_ayetul-kubra-p114-netice-dua-ve-kapanis-hamdi.txt",
  "sourceRevision": "e95533b783dc9d316f07878f65fcd0d07d571e1c66d5129c42ada623c62d35bf",
  "setCount": 6,
  "questionCount": 60,
  "sets": [
    {
      "setNumber": 1,
      "questions": [
        {
          "canonicalId": "ayetul-kubra:p114:5-sinif:S1Q1",
          "sourceQuestionId": "S1Q1",
          "sourceSetNumber": 1,
          "sourceQuestionNumber": 1,
          "question": "Bu bölümün başındaki Arapça cümlede kul, Allah karşısında kendi bilgisi için nasıl bir sınır kabul ediyor?",
          "answer": "İnsan, kendi başına her şeyi bilemeyeceğini; bildiği şeylerin Allah’ın öğretmesiyle olduğunu kabul ediyor.",
          "wordCount": 13,
          "hint": "",
          "dependsOn": []
        },
        {
          "canonicalId": "ayetul-kubra:p114:5-sinif:S1Q2",
          "sourceQuestionId": "S1Q2",
          "sourceSetNumber": 1,
          "sourceQuestionNumber": 2,
          "question": "İlk duada Allah’ın hangi iki sıfatı özellikle anılıyor?",
          "answer": "Rahmân ve Rahîm isimleri anılıyor.",
          "wordCount": 5,
          "hint": "",
          "dependsOn": []
        },
        {
          "canonicalId": "ayetul-kubra:p114:5-sinif:S1Q3",
          "sourceQuestionId": "S1Q3",
          "sourceSetNumber": 1,
          "sourceQuestionNumber": 3,
          "question": "Salât ve selâm kimlerin üzerine isteniyor?",
          "answer": "Peygamber Efendimiz’in, ailesinin ve bütün ashâbının üzerine isteniyor.",
          "wordCount": 8,
          "hint": "",
          "dependsOn": []
        },
        {
          "canonicalId": "ayetul-kubra:p114:5-sinif:S1Q4",
          "sourceQuestionId": "S1Q4",
          "sourceSetNumber": 1,
          "sourceQuestionNumber": 4,
          "question": "Duada istenen salavatın çokluğu nasıl anlatılıyor?",
          "answer": "Çok büyük sayılarla, yazılan harfler ve insan ömründeki vakitler anılarak çok fazla olması dileniyor.",
          "wordCount": 14,
          "hint": "",
          "dependsOn": []
        },
        {
          "canonicalId": "ayetul-kubra:p114:5-sinif:S1Q5",
          "sourceQuestionId": "S1Q5",
          "sourceSetNumber": 1,
          "sourceQuestionNumber": 5,
          "question": "Duayı yapan kişi kendisi için Allah’tan ne istiyor?",
          "answer": "Bağışlanma diliyor.",
          "wordCount": 2,
          "hint": "",
          "dependsOn": []
        },
        {
          "canonicalId": "ayetul-kubra:p114:5-sinif:S1Q6",
          "sourceQuestionId": "S1Q6",
          "sourceSetNumber": 1,
          "sourceQuestionNumber": 6,
          "question": "Bağışlanma sadece bir kişi için mi isteniyor, başka kimler de duaya katılıyor?",
          "answer": "Başka kimler de katılıyor; yardım edenler, anne babalar, büyükler, kardeşler ve samimi talebeler için de isteniyor.",
          "wordCount": 16,
          "hint": "",
          "dependsOn": []
        },
        {
          "canonicalId": "ayetul-kubra:p114:5-sinif:S1Q7",
          "sourceQuestionId": "S1Q7",
          "sourceSetNumber": 1,
          "sourceQuestionNumber": 7,
          "question": "Risalelerin yayılmasına yardım edenler için nasıl bir dua ediliyor?",
          "answer": "Bu hizmete dostlukla yardım edenlerin affedilmesi ve hayırla anılması isteniyor.",
          "wordCount": 10,
          "hint": "",
          "dependsOn": []
        },
        {
          "canonicalId": "ayetul-kubra:p114:5-sinif:S1Q8",
          "sourceQuestionId": "S1Q8",
          "sourceSetNumber": 1,
          "sourceQuestionNumber": 8,
          "question": "Özellikle hangi kimseler ayrıca zikrediliyor?",
          "answer": "Bu risaleyi yazan ve çoğaltan kimseler ayrıca anılıyor.",
          "wordCount": 8,
          "hint": "",
          "dependsOn": []
        },
        {
          "canonicalId": "ayetul-kubra:p114:5-sinif:S1Q9",
          "sourceQuestionId": "S1Q9",
          "sourceSetNumber": 1,
          "sourceQuestionNumber": 9,
          "question": "Duanın sonunda Allah’a hangi yönüyle yalvarılıyor?",
          "answer": "Merhametinin çok geniş olmasıyla yalvarılıyor.",
          "wordCount": 5,
          "hint": "",
          "dependsOn": []
        },
        {
          "canonicalId": "ayetul-kubra:p114:5-sinif:S1Q10",
          "sourceQuestionId": "S1Q10",
          "sourceSetNumber": 1,
          "sourceQuestionNumber": 10,
          "question": "En sondaki kısa cümlede sözün nasıl bitirildiği bildiriliyor?",
          "answer": "Sonun hamd ile, yani âlemlerin Rabbi olan Allah’a şükürle tamamlandığı bildiriliyor.",
          "wordCount": 11,
          "hint": "",
          "dependsOn": []
        }
      ]
    },
    {
      "setNumber": 2,
      "questions": [
        {
          "canonicalId": "ayetul-kubra:p114:5-sinif:S2Q1",
          "sourceQuestionId": "S2Q1",
          "sourceSetNumber": 2,
          "sourceQuestionNumber": 1,
          "question": "Metindeki dua, insanın ilim konusunda hangi güzel edebi öğretiyor?",
          "answer": "İnsan, bilgisini kendinden bilmeyip Allah’tan geldiğini anlamalıdır.",
          "wordCount": 7,
          "hint": "",
          "dependsOn": []
        },
        {
          "canonicalId": "ayetul-kubra:p114:5-sinif:S2Q2",
          "sourceQuestionId": "S2Q2",
          "sourceSetNumber": 2,
          "sourceQuestionNumber": 2,
          "question": "Besmele ile birlikte Allah’a seslenilmesi duanın hangi özelliğini gösterir?",
          "answer": "Duanın saygı, teslimiyet ve Allah’ın rahmetine sığınma içinde yapıldığını gösterir.",
          "wordCount": 10,
          "hint": "",
          "dependsOn": []
        },
        {
          "canonicalId": "ayetul-kubra:p114:5-sinif:S2Q3",
          "sourceQuestionId": "S2Q3",
          "sourceSetNumber": 2,
          "sourceQuestionNumber": 3,
          "question": "Peygamberimize salât ve selâm getirilmesi, duanın hangi İslâmî yönünü gösterir?",
          "answer": "Müslümanın duasında Resûlullah’a sevgi ve hürmet göstermesi gerektiğini gösterir.",
          "wordCount": 9,
          "hint": "",
          "dependsOn": []
        },
        {
          "canonicalId": "ayetul-kubra:p114:5-sinif:S2Q4",
          "sourceQuestionId": "S2Q4",
          "sourceSetNumber": 2,
          "sourceQuestionNumber": 4,
          "question": "Harfler, dakikalar ve zerreler gibi çokluk ifadeleri niçin kullanılmış olabilir?",
          "answer": "Salavatın ve duanın çok bol olması istendiği için kullanılmış olabilir.",
          "wordCount": 10,
          "hint": "",
          "dependsOn": []
        },
        {
          "canonicalId": "ayetul-kubra:p114:5-sinif:S2Q5",
          "sourceQuestionId": "S2Q5",
          "sourceSetNumber": 2,
          "sourceQuestionNumber": 5,
          "question": "Metinde yalnız dua eden kişinin kendisi mi düşünülüyor?",
          "answer": "Hayır, çevresindeki birçok insan da duaya dâhil ediliyor.",
          "wordCount": 8,
          "hint": "",
          "dependsOn": []
        },
        {
          "canonicalId": "ayetul-kubra:p114:5-sinif:S2Q6",
          "sourceQuestionId": "S2Q6",
          "sourceSetNumber": 2,
          "sourceQuestionNumber": 6,
          "question": "Hangi yakınlar ve topluluklar duada yer alıyor?",
          "answer": "Anne babalar, büyükler, hocalar, kardeşler ve samimi talebeler yer alıyor.",
          "wordCount": 10,
          "hint": "",
          "dependsOn": []
        },
        {
          "canonicalId": "ayetul-kubra:p114:5-sinif:S2Q7",
          "sourceQuestionId": "S2Q7",
          "sourceSetNumber": 2,
          "sourceQuestionNumber": 7,
          "question": "Nurların yayılması ve yazılması için çalışanlara dua edilmesi bize hangi değeri öğretir?",
          "answer": "Dine ve hayra hizmet edenlere vefa göstermeyi öğretir.",
          "wordCount": 8,
          "hint": "",
          "dependsOn": []
        },
        {
          "canonicalId": "ayetul-kubra:p114:5-sinif:S2Q8",
          "sourceQuestionId": "S2Q8",
          "sourceSetNumber": 2,
          "sourceQuestionNumber": 8,
          "question": "Yazıp çoğaltanların özellikle anılması neden önemli görülebilir?",
          "answer": "Çünkü onlar faydalı bilginin başkalarına ulaşmasına emek veriyorlar.",
          "wordCount": 8,
          "hint": "",
          "dependsOn": []
        },
        {
          "canonicalId": "ayetul-kubra:p114:5-sinif:S2Q9",
          "sourceQuestionId": "S2Q9",
          "sourceSetNumber": 2,
          "sourceQuestionNumber": 9,
          "question": "“Ey merhametlilerin en merhametlisi” diye yakarmak Allah’tan ne beklemeyi ifade eder?",
          "answer": "Büyük bir ümit ve rahmet beklemeyi ifade eder.",
          "wordCount": 8,
          "hint": "",
          "dependsOn": []
        },
        {
          "canonicalId": "ayetul-kubra:p114:5-sinif:S2Q10",
          "sourceQuestionId": "S2Q10",
          "sourceSetNumber": 2,
          "sourceQuestionNumber": 10,
          "question": "Son cümlede hamd ile bitirilmesi, duanın genel havasını nasıl tamamlar?",
          "answer": "Dua, şükür ve Allah’ı övme ile güzelce tamamlanmış olur.",
          "wordCount": 9,
          "hint": "",
          "dependsOn": []
        }
      ]
    },
    {
      "setNumber": 3,
      "questions": [
        {
          "canonicalId": "ayetul-kubra:p114:5-sinif:S3Q1",
          "sourceQuestionId": "S3Q1",
          "sourceSetNumber": 3,
          "sourceQuestionNumber": 1,
          "question": "Bu bölümde önce hangi iki ana şey görülür: bilgiyle ilgili bir kabul mü, yoksa bir olay anlatımı mı?",
          "answer": "Önce bilgiyle ilgili bir kabul görülür.",
          "wordCount": 6,
          "hint": "",
          "dependsOn": []
        },
        {
          "canonicalId": "ayetul-kubra:p114:5-sinif:S3Q2",
          "sourceQuestionId": "S3Q2",
          "sourceSetNumber": 3,
          "sourceQuestionNumber": 2,
          "question": "Kulun “bildiğimiz Senin öğrettiğin kadardır” anlamındaki sözü hangi duyguyu taşır?",
          "answer": "Tevazu ve kulluk duygusunu taşır.",
          "wordCount": 5,
          "hint": "",
          "dependsOn": []
        },
        {
          "canonicalId": "ayetul-kubra:p114:5-sinif:S3Q3",
          "sourceQuestionId": "S3Q3",
          "sourceSetNumber": 3,
          "sourceQuestionNumber": 3,
          "question": "Allah’a “Allah, Rahmân, Rahîm” diye hitap edilmesi O’nun hangi yönlerini öne çıkarır?",
          "answer": "İlâhlığını ve merhametini öne çıkarır.",
          "wordCount": 5,
          "hint": "",
          "dependsOn": []
        },
        {
          "canonicalId": "ayetul-kubra:p114:5-sinif:S3Q4",
          "sourceQuestionId": "S3Q4",
          "sourceSetNumber": 3,
          "sourceQuestionNumber": 4,
          "question": "Peygamber Efendimiz’den sonra kimler anılıyor?",
          "answer": "Ailesi ve sahâbeleri anılıyor.",
          "wordCount": 4,
          "hint": "",
          "dependsOn": []
        },
        {
          "canonicalId": "ayetul-kubra:p114:5-sinif:S3Q5",
          "sourceQuestionId": "S3Q5",
          "sourceSetNumber": 3,
          "sourceQuestionNumber": 5,
          "question": "Salavatın sayısı anlatılırken neden sıradan küçük sayılar yerine çok geniş ifadeler seçilmiş olabilir?",
          "answer": "Çok büyük bir sevgi ve çokça dua etme isteği gösterilmek istenmiştir.",
          "wordCount": 11,
          "hint": "",
          "dependsOn": []
        },
        {
          "canonicalId": "ayetul-kubra:p114:5-sinif:S3Q6",
          "sourceQuestionId": "S3Q6",
          "sourceSetNumber": 3,
          "sourceQuestionNumber": 6,
          "question": "Dua eden kişi, Risale-i Nur’un yayılmasında yardım edenlere karşı nasıl bir tavır içindedir?",
          "answer": "Onlara dua eden, iyiliklerini unutmayan bir tavır içindedir.",
          "wordCount": 8,
          "hint": "",
          "dependsOn": []
        },
        {
          "canonicalId": "ayetul-kubra:p114:5-sinif:S3Q7",
          "sourceQuestionId": "S3Q7",
          "sourceSetNumber": 3,
          "sourceQuestionNumber": 7,
          "question": "Metinde kardeşlik bağı sadece aile ile mi sınırlı tutuluyor?",
          "answer": "Hayır, din kardeşleri ve talebeler de bu bağ içinde anılıyor.",
          "wordCount": 10,
          "hint": "",
          "dependsOn": []
        },
        {
          "canonicalId": "ayetul-kubra:p114:5-sinif:S3Q8",
          "sourceQuestionId": "S3Q8",
          "sourceSetNumber": 3,
          "sourceQuestionNumber": 8,
          "question": "“Sadakatle” yapılan yardımın anılması, hizmette hangi ahlâkı öne çıkarır?",
          "answer": "İçtenlik ve bağlılık ahlâkını öne çıkarır.",
          "wordCount": 6,
          "hint": "",
          "dependsOn": []
        },
        {
          "canonicalId": "ayetul-kubra:p114:5-sinif:S3Q9",
          "sourceQuestionId": "S3Q9",
          "sourceSetNumber": 3,
          "sourceQuestionNumber": 9,
          "question": "Sonunda “âmin” denmesi neyi gösterir?",
          "answer": "Yapılan duanın kabul edilmesi için Allah’a yönelindiğini gösterir.",
          "wordCount": 8,
          "hint": "",
          "dependsOn": []
        },
        {
          "canonicalId": "ayetul-kubra:p114:5-sinif:S3Q10",
          "sourceQuestionId": "S3Q10",
          "sourceSetNumber": 3,
          "sourceQuestionNumber": 10,
          "question": "En son hamd edilmesi, duanın başındaki ilim duasıyla birlikte düşünülünce hangi güzel sonucu verir?",
          "answer": "İnsan hem Allah’tan öğrenmeyi ister hem de sonunda O’na şükretmiş olur.",
          "wordCount": 11,
          "hint": "",
          "dependsOn": []
        }
      ]
    },
    {
      "setNumber": 4,
      "questions": [
        {
          "canonicalId": "ayetul-kubra:p114:5-sinif:S4Q1",
          "sourceQuestionId": "S4Q1",
          "sourceSetNumber": 4,
          "sourceQuestionNumber": 1,
          "question": "Bu parçada insanın ilmi kendi gücüne değil, kime bağlanıyor?",
          "answer": "Allah’a bağlanıyor.",
          "wordCount": 2,
          "hint": "",
          "dependsOn": []
        },
        {
          "canonicalId": "ayetul-kubra:p114:5-sinif:S4Q2",
          "sourceQuestionId": "S4Q2",
          "sourceSetNumber": 4,
          "sourceQuestionNumber": 2,
          "question": "Allah’ın hem bilen hem hikmet sahibi oluşu, kul için neden güven vericidir?",
          "answer": "Çünkü Allah her şeyi bilir ve her işi hikmetle yapar.",
          "wordCount": 10,
          "hint": "",
          "dependsOn": []
        },
        {
          "canonicalId": "ayetul-kubra:p114:5-sinif:S4Q3",
          "sourceQuestionId": "S4Q3",
          "sourceSetNumber": 4,
          "sourceQuestionNumber": 3,
          "question": "Metinde Peygamberimize dua edilmesi Müslüman çocuklara hangi alışkanlığı hatırlatır?",
          "answer": "Resûlullah’a salavat getirme alışkanlığını hatırlatır.",
          "wordCount": 5,
          "hint": "",
          "dependsOn": []
        },
        {
          "canonicalId": "ayetul-kubra:p114:5-sinif:S4Q4",
          "sourceQuestionId": "S4Q4",
          "sourceSetNumber": 4,
          "sourceQuestionNumber": 4,
          "question": "Duadaki büyük sayı anlatımları gerçek bir hesap vermekten çok hangi mesajı taşıyor?",
          "answer": "Çokluk, bereket ve bolca dua isteği mesajını taşıyor.",
          "wordCount": 8,
          "hint": "",
          "dependsOn": []
        },
        {
          "canonicalId": "ayetul-kubra:p114:5-sinif:S4Q5",
          "sourceQuestionId": "S4Q5",
          "sourceSetNumber": 4,
          "sourceQuestionNumber": 5,
          "question": "Dua eden kişi sadece kendini düşünen biri gibi mi görünüyor?",
          "answer": "Hayır, başkalarını da düşünen biri gibi görünüyor.",
          "wordCount": 7,
          "hint": "",
          "dependsOn": []
        },
        {
          "canonicalId": "ayetul-kubra:p114:5-sinif:S4Q6",
          "sourceQuestionId": "S4Q6",
          "sourceSetNumber": 4,
          "sourceQuestionNumber": 6,
          "question": "Hangi kişiler için af ve rahmet isteniyor?",
          "answer": "Yardım edenler, anne babalar, büyükler, şeyhler, kardeşler, samimi talebeler ve bu metni yazıp çoğaltanlar için isteniyor.",
          "wordCount": 16,
          "hint": "",
          "dependsOn": []
        },
        {
          "canonicalId": "ayetul-kubra:p114:5-sinif:S4Q7",
          "sourceQuestionId": "S4Q7",
          "sourceSetNumber": 4,
          "sourceQuestionNumber": 7,
          "question": "Yazma ve çoğaltma işini yapanlara özel dua edilmesi, bilginin yayılması hakkında ne anlatır?",
          "answer": "Faydalı ilmin yayılmasının değerli bir hizmet olduğunu anlatır.",
          "wordCount": 8,
          "hint": "",
          "dependsOn": []
        },
        {
          "canonicalId": "ayetul-kubra:p114:5-sinif:S4Q8",
          "sourceQuestionId": "S4Q8",
          "sourceSetNumber": 4,
          "sourceQuestionNumber": 8,
          "question": "Duanın sonunda rahmete sığınmak, kulun Allah’la ilişkisini nasıl gösterir?",
          "answer": "Muhtaç, umutlu ve teslim olmuş bir kul ilişkisi gösterir.",
          "wordCount": 9,
          "hint": "",
          "dependsOn": []
        },
        {
          "canonicalId": "ayetul-kubra:p114:5-sinif:S4Q9",
          "sourceQuestionId": "S4Q9",
          "sourceSetNumber": 4,
          "sourceQuestionNumber": 9,
          "question": "Sondaki kısa ayet anlamca neyi öne çıkarır?",
          "answer": "Her şeyin sonunda övgü ve şükrün Allah’a ait olduğunu öne çıkarır.",
          "wordCount": 11,
          "hint": "",
          "dependsOn": []
        },
        {
          "canonicalId": "ayetul-kubra:p114:5-sinif:S4Q10",
          "sourceQuestionId": "S4Q10",
          "sourceSetNumber": 4,
          "sourceQuestionNumber": 10,
          "question": "Bu parçanın genel konusu en kısa nasıl söylenebilir?",
          "answer": "Allah’a yönelen bir dua, salavat ve bağışlanma isteğidir.",
          "wordCount": 8,
          "hint": "",
          "dependsOn": []
        }
      ]
    },
    {
      "setNumber": 5,
      "questions": [
        {
          "canonicalId": "ayetul-kubra:p114:5-sinif:S5Q1",
          "sourceQuestionId": "S5Q1",
          "sourceSetNumber": 5,
          "sourceQuestionNumber": 1,
          "question": "Parçanın başında geçen ifade, öğrenmenin asıl kaynağı olarak neyi gösteriyor?",
          "answer": "Asıl kaynağın Allah’ın öğretmesi olduğunu gösteriyor.",
          "wordCount": 6,
          "hint": "",
          "dependsOn": []
        },
        {
          "canonicalId": "ayetul-kubra:p114:5-sinif:S5Q2",
          "sourceQuestionId": "S5Q2",
          "sourceSetNumber": 5,
          "sourceQuestionNumber": 2,
          "question": "Allah’ın isimleri arasında merhameti bildiren hangileri geçiyor?",
          "answer": "Rahmân ve Rahîm geçiyor.",
          "wordCount": 4,
          "hint": "",
          "dependsOn": []
        },
        {
          "canonicalId": "ayetul-kubra:p114:5-sinif:S5Q3",
          "sourceQuestionId": "S5Q3",
          "sourceSetNumber": 5,
          "sourceQuestionNumber": 3,
          "question": "Peygamberimize edilen duaya kimler ortak ediliyor?",
          "answer": "Âli ve ashâbı da ortak ediliyor.",
          "wordCount": 6,
          "hint": "",
          "dependsOn": []
        },
        {
          "canonicalId": "ayetul-kubra:p114:5-sinif:S5Q4",
          "sourceQuestionId": "S5Q4",
          "sourceSetNumber": 5,
          "sourceQuestionNumber": 4,
          "question": "Salavatın çokluğunu anlatan ifadeler okuyucuya nasıl bir his verir?",
          "answer": "Genişlik, bolluk ve derin muhabbet hissi verir.",
          "wordCount": 7,
          "hint": "",
          "dependsOn": []
        },
        {
          "canonicalId": "ayetul-kubra:p114:5-sinif:S5Q5",
          "sourceQuestionId": "S5Q5",
          "sourceSetNumber": 5,
          "sourceQuestionNumber": 5,
          "question": "Dua edenin kendisi için istediği şey nedir?",
          "answer": "Affedilmektir.",
          "wordCount": 1,
          "hint": "",
          "dependsOn": []
        },
        {
          "canonicalId": "ayetul-kubra:p114:5-sinif:S5Q6",
          "sourceQuestionId": "S5Q6",
          "sourceSetNumber": 5,
          "sourceQuestionNumber": 6,
          "question": "Yardım edenler için dua edilmesi hangi güzel davranışı gösterir?",
          "answer": "Teşekkür etmeyi ve iyiliği unutmamayı gösterir.",
          "wordCount": 6,
          "hint": "",
          "dependsOn": []
        },
        {
          "canonicalId": "ayetul-kubra:p114:5-sinif:S5Q7",
          "sourceQuestionId": "S5Q7",
          "sourceSetNumber": 5,
          "sourceQuestionNumber": 7,
          "question": "Anne babalarla birlikte başka hangi grupların anılması, duanın kapsayıcılığı hakkında ne söyler?",
          "answer": "Duanın sadece aileye değil, daha geniş bir iman kardeşliği çevresine yöneldiğini söyler.",
          "wordCount": 12,
          "hint": "",
          "dependsOn": []
        },
        {
          "canonicalId": "ayetul-kubra:p114:5-sinif:S5Q8",
          "sourceQuestionId": "S5Q8",
          "sourceSetNumber": 5,
          "sourceQuestionNumber": 8,
          "question": "Özellikle metni yazan ve çoğaltanların anılması hangi emeğin fark edildiğini gösterir?",
          "answer": "Hizmet için verilen yazı ve çoğaltma emeğinin fark edildiğini gösterir.",
          "wordCount": 10,
          "hint": "",
          "dependsOn": []
        },
        {
          "canonicalId": "ayetul-kubra:p114:5-sinif:S5Q9",
          "sourceQuestionId": "S5Q9",
          "sourceSetNumber": 5,
          "sourceQuestionNumber": 9,
          "question": "“Âmin” ifadesinin burada görevi nedir?",
          "answer": "Yapılan yakarışın kabulünü istemektir.",
          "wordCount": 4,
          "hint": "",
          "dependsOn": []
        },
        {
          "canonicalId": "ayetul-kubra:p114:5-sinif:S5Q10",
          "sourceQuestionId": "S5Q10",
          "sourceSetNumber": 5,
          "sourceQuestionNumber": 10,
          "question": "Hamd ile bitirmek, Müslümanın duasında hangi dengeyi gösterir?",
          "answer": "İstemekle birlikte şükretmeyi de unutmama dengesini gösterir.",
          "wordCount": 7,
          "hint": "",
          "dependsOn": []
        }
      ]
    },
    {
      "setNumber": 6,
      "questions": [
        {
          "canonicalId": "ayetul-kubra:p114:5-sinif:S6Q1",
          "sourceQuestionId": "S6Q1",
          "sourceSetNumber": 6,
          "sourceQuestionNumber": 1,
          "question": "Bu bölümde insanın bilgi bakımından ilk söylediği şey güçlülüğü mü, eksikliği mi?",
          "answer": "Eksikliğidir.",
          "wordCount": 1,
          "hint": "",
          "dependsOn": []
        },
        {
          "canonicalId": "ayetul-kubra:p114:5-sinif:S6Q2",
          "sourceQuestionId": "S6Q2",
          "sourceSetNumber": 6,
          "sourceQuestionNumber": 2,
          "question": "Allah’a birden fazla isimle seslenilmesi duayı nasıl etkiler?",
          "answer": "Duayı daha içten, saygılı ve anlamlı hâle getirir.",
          "wordCount": 8,
          "hint": "",
          "dependsOn": []
        },
        {
          "canonicalId": "ayetul-kubra:p114:5-sinif:S6Q3",
          "sourceQuestionId": "S6Q3",
          "sourceSetNumber": 6,
          "sourceQuestionNumber": 3,
          "question": "Peygamber Efendimiz için salât ve selâm istenirken onun yanında kimler de zikredilir?",
          "answer": "Ailesi ve bütün sahâbeleri zikredilir.",
          "wordCount": 5,
          "hint": "",
          "dependsOn": []
        },
        {
          "canonicalId": "ayetul-kubra:p114:5-sinif:S6Q4",
          "sourceQuestionId": "S6Q4",
          "sourceSetNumber": 6,
          "sourceQuestionNumber": 4,
          "question": "Salavatın sayısı anlatılırken ömür, vakit ve zerrelerden söz edilmesi neyi düşündürür?",
          "answer": "Çok geniş bir ölçüde dua edilmek istendiğini düşündürür.",
          "wordCount": 8,
          "hint": "",
          "dependsOn": []
        },
        {
          "canonicalId": "ayetul-kubra:p114:5-sinif:S6Q5",
          "sourceQuestionId": "S6Q5",
          "sourceSetNumber": 6,
          "sourceQuestionNumber": 5,
          "question": "Metinde bağışlanma talebi yalnız dua eden kişiye mi aittir?",
          "answer": "Hayır, birçok kişiyi içine alır.",
          "wordCount": 5,
          "hint": "",
          "dependsOn": []
        },
        {
          "canonicalId": "ayetul-kubra:p114:5-sinif:S6Q6",
          "sourceQuestionId": "S6Q6",
          "sourceSetNumber": 6,
          "sourceQuestionNumber": 6,
          "question": "Dua halkasına giren kişiler arasında hangi hizmet sahipleri vardır?",
          "answer": "Risalelerin yayılmasına yardım edenler ile onları yazan ve çoğaltanlar vardır.",
          "wordCount": 10,
          "hint": "",
          "dependsOn": []
        },
        {
          "canonicalId": "ayetul-kubra:p114:5-sinif:S6Q7",
          "sourceQuestionId": "S6Q7",
          "sourceSetNumber": 6,
          "sourceQuestionNumber": 7,
          "question": "Samimi talebelerin özellikle anılması hangi özelliğin değerli görüldüğünü gösterir?",
          "answer": "Doğruluk ve samimiyetin değerli görüldüğünü gösterir.",
          "wordCount": 6,
          "hint": "",
          "dependsOn": []
        },
        {
          "canonicalId": "ayetul-kubra:p114:5-sinif:S6Q8",
          "sourceQuestionId": "S6Q8",
          "sourceSetNumber": 6,
          "sourceQuestionNumber": 8,
          "question": "Allah’tan rahmet istenmesi ile hamd edilmesi arasında nasıl bir ilişki vardır?",
          "answer": "Kul önce rahmet ister, sonra Allah’ı överek teslimiyetini gösterir.",
          "wordCount": 9,
          "hint": "",
          "dependsOn": []
        },
        {
          "canonicalId": "ayetul-kubra:p114:5-sinif:S6Q9",
          "sourceQuestionId": "S6Q9",
          "sourceSetNumber": 6,
          "sourceQuestionNumber": 9,
          "question": "Bu parçadan, Müslümanın duasının sadece kendine dönük olmaması hakkında ne çıkarılır?",
          "answer": "Müslüman, başkalarını da düşünerek topluca dua etmelidir.",
          "wordCount": 7,
          "hint": "",
          "dependsOn": []
        },
        {
          "canonicalId": "ayetul-kubra:p114:5-sinif:S6Q10",
          "sourceQuestionId": "S6Q10",
          "sourceSetNumber": 6,
          "sourceQuestionNumber": 10,
          "question": "Parçanın tamamına bakınca öne çıkan üç ana unsur nedir?",
          "answer": "Allah’tan ilim ve rahmet istemek, Peygamberimize salavat getirmek ve müminler için bağışlanma dilemektir.",
          "wordCount": 13,
          "hint": "",
          "dependsOn": []
        }
      ]
    }
  ]
}
